gcode_helpers/__init__.py
gcode_helpers/gcode_helpers.py
gcode_helpers-0.3.0.dist-info/METADATA
gcode_helpers-0.3.0.dist-info/WHEEL
gcode_helpers-0.3.0.dist-info/RECORD
